{
  "_class": "symbolInstance",
  "booleanOperation": -1,
  "clippingMaskMode": 0,
  "do_objectID": "A20A4C68-F53E-4D3C-9531-D0CDEA54E834",
  "exportOptions": {
    "_class": "exportOptions",
    "do_objectID": "126D1733-FAC7-4619-9989-A802706267A8",
    "exportFormats": [
    ],
    "includedLayerIds": [
    ],
    "layerOptions": 0,
    "shouldTrim": false
  },
  "frame": {
    "_class": "rect",
    "constrainProportions": false,
    "do_objectID": "EC0DC2CF-1A83-4052-BC22-BD253B5D8471",
    "height": 344,
    "width": 1440,
    "x": -1846,
    "y": 3739
  },
  "hasClippingMask": false,
  "horizontalSpacing": 0,
  "isFixedToViewport": false,
  "isFlippedHorizontal": false,
  "isFlippedVertical": false,
  "isLocked": false,
  "isVisible": true,
  "layerListExpandedType": 0,
  "name": "footer",
  "nameIsFixed": false,
  "overrideValues": [
  ],
  "resizingConstraint": 63,
  "resizingType": 0,
  "rotation": 0,
  "scale": 1,
  "shouldBreakMaskChain": false,
  "style": {
    "_class": "style",
    "do_objectID": "64A1AE73-953A-4937-A74C-47618D0C7662",
    "endMarkerType": 0,
    "miterLimit": 10,
    "startMarkerType": 0,
    "windingRule": 1
  },
  "symbolID": "FB9C4428-7D69-48F0-A6AE-9C4EC863FFFA",
  "verticalSpacing": 0
}